oxiida-0.1.0a2.dist-info/METADATA
oxiida-0.1.0a2.dist-info/WHEEL
oxiida/oxiida.pyi
oxiida/__init__.py
oxiida/oxiida.abi3.so
oxiida-0.1.0a2.dist-info/RECORD
