Metadata-Version: 2.4
Name: oxiida
Version: 0.1.0a2
Classifier: Programming Language :: Rust
Classifier: Programming Language :: Python :: Implementation :: CPython
Classifier: License :: OSI Approved :: Apache Software License
Classifier: License :: OSI Approved :: MIT License
Requires-Dist: pytest~=8.3 ; extra == 'tests'
Provides-Extra: tests
Summary: A DSL for scientific workflow construction.
Home-Page: https://github.com/unkcpz/oxiida
Author: you
Author-email: Jusong Yu <jusong.d.yu@gmail.com>
License: Apache-2.0 OR MIT
Requires-Python: >=3.10
